{
  "stac_version" : "0.9.0",
  "stac_extensions" : [
    "eo",
    "view",
    "https://example.com/stac/landsat-extension/1.0/schema.json"
  ],
  "id" : "layer-pa",
  "title" : "Landsat 8 L1",
  "description" : "PA STAC Layer",
  "links" : [
    {
      "href" : "../../catalog.json",
      "rel" : "root"
    },
    {
      "href" : "../../catalog.json",
      "rel" : "parent"
    },
    {
      "href" : "./catalog.json",
      "rel" : "self"
    },
    {
      "href" : "../../landsat-8-l1/2018-06/LC80140332018166LGN00.json",
      "rel" : "item"
    },
    {
      "href" : "../../landsat-8-l1/2018-05/LC80150322018141LGN00.json",
      "rel" : "item"
    },
    {
      "href" : "../../landsat-8-l1/2018-07/LC80150332018189LGN00.json",
      "rel" : "item"
    }
  ]
}
